{
  "id": "66f11764-5a20-4218-a64b-a7499e415a11",
  "prevId": "00000000-0000-0000-0000-000000000000",
  "version": "7",
  "dialect": "postgresql",
  "tables": {
    "docai.chunks": {
      "name": "chunks",
      "schema": "docai",
      "columns": {
        "id": {
          "name": "id",
          "type": "uuid",
          "primaryKey": true,
          "notNull": true,
          "default": "gen_random_uuid()"
        },
        "document_id": {
          "name": "document_id",
          "type": "uuid",
          "primaryKey": false,
          "notNull": true
        },
        "workspace_id": {
          "name": "workspace_id",
          "type": "uuid",
          "primaryKey": false,
          "notNull": true
        },
        "chunk_index": {
          "name": "chunk_index",
          "type": "integer",
          "primaryKey": false,
          "notNull": true
        },
        "content": {
          "name": "content",
          "type": "text",
          "primaryKey": false,
          "notNull": true
        },
        "page": {
          "name": "page",
          "type": "integer",
          "primaryKey": false,
          "notNull": false
        },
        "token_count": {
          "name": "token_count",
          "type": "integer",
          "primaryKey": false,
          "notNull": true,
          "default": 0
        },
        "embedding": {
          "name": "embedding",
          "type": "vector(1024)",
          "primaryKey": false,
          "notNull": false
        },
        "tsv": {
          "name": "tsv",
          "type": "tsvector",
          "primaryKey": false,
          "notNull": false,
          "generated": {
            "as": "to_tsvector('simple', \"content\")",
            "type": "stored"
          }
        },
        "created_at": {
          "name": "created_at",
          "type": "timestamp with time zone",
          "primaryKey": false,
          "notNull": true,
          "default": "now()"
        }
      },
      "indexes": {
        "chunks_document_idx": {
          "name": "chunks_document_idx",
          "columns": [
            {
              "expression": "document_id",
              "isExpression": false,
              "asc": true,
              "nulls": "last"
            }
          ],
          "isUnique": false,
          "concurrently": false,
          "method": "btree",
          "with": {}
        },
        "chunks_workspace_idx": {
          "name": "chunks_workspace_idx",
          "columns": [
            {
              "expression": "workspace_id",
              "isExpression": false,
              "asc": true,
              "nulls": "last"
            }
          ],
          "isUnique": false,
          "concurrently": false,
          "method": "btree",
          "with": {}
        },
        "chunks_embedding_hnsw_idx": {
          "name": "chunks_embedding_hnsw_idx",
          "columns": [
            {
              "expression": "embedding",
              "isExpression": false,
              "asc": true,
              "nulls": "last",
              "opclass": "vector_cosine_ops"
            }
          ],
          "isUnique": false,
          "concurrently": false,
          "method": "hnsw",
          "with": {
            "m": 16,
            "ef_construction": 64
          }
        },
        "chunks_tsv_gin_idx": {
          "name": "chunks_tsv_gin_idx",
          "columns": [
            {
              "expression": "tsv",
              "isExpression": false,
              "asc": true,
              "nulls": "last"
            }
          ],
          "isUnique": false,
          "concurrently": false,
          "method": "gin",
          "with": {}
        }
      },
      "foreignKeys": {
        "chunks_document_id_documents_id_fk": {
          "name": "chunks_document_id_documents_id_fk",
          "tableFrom": "chunks",
          "tableTo": "documents",
          "schemaTo": "docai",
          "columnsFrom": [
            "document_id"
          ],
          "columnsTo": [
            "id"
          ],
          "onDelete": "cascade",
          "onUpdate": "no action"
        },
        "chunks_workspace_id_workspaces_id_fk": {
          "name": "chunks_workspace_id_workspaces_id_fk",
          "tableFrom": "chunks",
          "tableTo": "workspaces",
          "schemaTo": "docai",
          "columnsFrom": [
            "workspace_id"
          ],
          "columnsTo": [
            "id"
          ],
          "onDelete": "cascade",
          "onUpdate": "no action"
        }
      },
      "compositePrimaryKeys": {},
      "uniqueConstraints": {},
      "policies": {},
      "checkConstraints": {},
      "isRLSEnabled": false
    },
    "docai.documents": {
      "name": "documents",
      "schema": "docai",
      "columns": {
        "id": {
          "name": "id",
          "type": "uuid",
          "primaryKey": true,
          "notNull": true,
          "default": "gen_random_uuid()"
        },
        "workspace_id": {
          "name": "workspace_id",
          "type": "uuid",
          "primaryKey": false,
          "notNull": true
        },
        "uploader_id": {
          "name": "uploader_id",
          "type": "text",
          "primaryKey": false,
          "notNull": false
        },
        "filename": {
          "name": "filename",
          "type": "text",
          "primaryKey": false,
          "notNull": true
        },
        "r2_key": {
          "name": "r2_key",
          "type": "text",
          "primaryKey": false,
          "notNull": true
        },
        "status": {
          "name": "status",
          "type": "text",
          "primaryKey": false,
          "notNull": true,
          "default": "'uploading'"
        },
        "page_count": {
          "name": "page_count",
          "type": "integer",
          "primaryKey": false,
          "notNull": false
        },
        "byte_size": {
          "name": "byte_size",
          "type": "integer",
          "primaryKey": false,
          "notNull": false
        },
        "chunk_count": {
          "name": "chunk_count",
          "type": "integer",
          "primaryKey": false,
          "notNull": true,
          "default": 0
        },
        "total_tokens": {
          "name": "total_tokens",
          "type": "integer",
          "primaryKey": false,
          "notNull": true,
          "default": 0
        },
        "cost_usd": {
          "name": "cost_usd",
          "type": "numeric(10, 6)",
          "primaryKey": false,
          "notNull": true,
          "default": "'0'"
        },
        "latency_ms": {
          "name": "latency_ms",
          "type": "integer",
          "primaryKey": false,
          "notNull": false
        },
        "error_variant": {
          "name": "error_variant",
          "type": "text",
          "primaryKey": false,
          "notNull": false
        },
        "expires_at": {
          "name": "expires_at",
          "type": "timestamp with time zone",
          "primaryKey": false,
          "notNull": true
        },
        "created_at": {
          "name": "created_at",
          "type": "timestamp with time zone",
          "primaryKey": false,
          "notNull": true,
          "default": "now()"
        },
        "updated_at": {
          "name": "updated_at",
          "type": "timestamp with time zone",
          "primaryKey": false,
          "notNull": true,
          "default": "now()"
        }
      },
      "indexes": {
        "documents_workspace_expires_idx": {
          "name": "documents_workspace_expires_idx",
          "columns": [
            {
              "expression": "workspace_id",
              "isExpression": false,
              "asc": true,
              "nulls": "last"
            },
            {
              "expression": "expires_at",
              "isExpression": false,
              "asc": true,
              "nulls": "last"
            }
          ],
          "isUnique": false,
          "concurrently": false,
          "method": "btree",
          "with": {}
        }
      },
      "foreignKeys": {
        "documents_workspace_id_workspaces_id_fk": {
          "name": "documents_workspace_id_workspaces_id_fk",
          "tableFrom": "documents",
          "tableTo": "workspaces",
          "schemaTo": "docai",
          "columnsFrom": [
            "workspace_id"
          ],
          "columnsTo": [
            "id"
          ],
          "onDelete": "cascade",
          "onUpdate": "no action"
        },
        "documents_uploader_id_users_id_fk": {
          "name": "documents_uploader_id_users_id_fk",
          "tableFrom": "documents",
          "tableTo": "users",
          "schemaTo": "docai",
          "columnsFrom": [
            "uploader_id"
          ],
          "columnsTo": [
            "id"
          ],
          "onDelete": "set null",
          "onUpdate": "no action"
        }
      },
      "compositePrimaryKeys": {},
      "uniqueConstraints": {},
      "policies": {},
      "checkConstraints": {},
      "isRLSEnabled": false
    },
    "docai.project_budget_usage": {
      "name": "project_budget_usage",
      "schema": "docai",
      "columns": {
        "day": {
          "name": "day",
          "type": "date",
          "primaryKey": true,
          "notNull": true
        },
        "cost_usd": {
          "name": "cost_usd",
          "type": "numeric(12, 6)",
          "primaryKey": false,
          "notNull": true,
          "default": "'0'"
        },
        "updated_at": {
          "name": "updated_at",
          "type": "timestamp with time zone",
          "primaryKey": false,
          "notNull": true,
          "default": "now()"
        }
      },
      "indexes": {},
      "foreignKeys": {},
      "compositePrimaryKeys": {},
      "uniqueConstraints": {},
      "policies": {},
      "checkConstraints": {},
      "isRLSEnabled": false
    },
    "docai.usage_events": {
      "name": "usage_events",
      "schema": "docai",
      "columns": {
        "id": {
          "name": "id",
          "type": "uuid",
          "primaryKey": true,
          "notNull": true,
          "default": "gen_random_uuid()"
        },
        "workspace_id": {
          "name": "workspace_id",
          "type": "uuid",
          "primaryKey": false,
          "notNull": false
        },
        "document_id": {
          "name": "document_id",
          "type": "uuid",
          "primaryKey": false,
          "notNull": false
        },
        "model": {
          "name": "model",
          "type": "text",
          "primaryKey": false,
          "notNull": true
        },
        "input_tokens": {
          "name": "input_tokens",
          "type": "integer",
          "primaryKey": false,
          "notNull": true,
          "default": 0
        },
        "output_tokens": {
          "name": "output_tokens",
          "type": "integer",
          "primaryKey": false,
          "notNull": true,
          "default": 0
        },
        "cost_usd": {
          "name": "cost_usd",
          "type": "numeric(10, 6)",
          "primaryKey": false,
          "notNull": true,
          "default": "'0'"
        },
        "latency_ms": {
          "name": "latency_ms",
          "type": "integer",
          "primaryKey": false,
          "notNull": false
        },
        "is_privileged": {
          "name": "is_privileged",
          "type": "boolean",
          "primaryKey": false,
          "notNull": true,
          "default": false
        },
        "created_at": {
          "name": "created_at",
          "type": "timestamp with time zone",
          "primaryKey": false,
          "notNull": true,
          "default": "now()"
        }
      },
      "indexes": {
        "usage_events_created_model_idx": {
          "name": "usage_events_created_model_idx",
          "columns": [
            {
              "expression": "created_at",
              "isExpression": false,
              "asc": true,
              "nulls": "last"
            },
            {
              "expression": "model",
              "isExpression": false,
              "asc": true,
              "nulls": "last"
            }
          ],
          "isUnique": false,
          "concurrently": false,
          "method": "btree",
          "with": {}
        }
      },
      "foreignKeys": {
        "usage_events_workspace_id_workspaces_id_fk": {
          "name": "usage_events_workspace_id_workspaces_id_fk",
          "tableFrom": "usage_events",
          "tableTo": "workspaces",
          "schemaTo": "docai",
          "columnsFrom": [
            "workspace_id"
          ],
          "columnsTo": [
            "id"
          ],
          "onDelete": "set null",
          "onUpdate": "no action"
        },
        "usage_events_document_id_documents_id_fk": {
          "name": "usage_events_document_id_documents_id_fk",
          "tableFrom": "usage_events",
          "tableTo": "documents",
          "schemaTo": "docai",
          "columnsFrom": [
            "document_id"
          ],
          "columnsTo": [
            "id"
          ],
          "onDelete": "set null",
          "onUpdate": "no action"
        }
      },
      "compositePrimaryKeys": {},
      "uniqueConstraints": {},
      "policies": {},
      "checkConstraints": {},
      "isRLSEnabled": false
    },
    "docai.users": {
      "name": "users",
      "schema": "docai",
      "columns": {
        "id": {
          "name": "id",
          "type": "text",
          "primaryKey": true,
          "notNull": true
        },
        "email": {
          "name": "email",
          "type": "text",
          "primaryKey": false,
          "notNull": true
        },
        "created_at": {
          "name": "created_at",
          "type": "timestamp with time zone",
          "primaryKey": false,
          "notNull": true,
          "default": "now()"
        }
      },
      "indexes": {},
      "foreignKeys": {},
      "compositePrimaryKeys": {},
      "uniqueConstraints": {},
      "policies": {},
      "checkConstraints": {},
      "isRLSEnabled": false
    },
    "docai.workspaces": {
      "name": "workspaces",
      "schema": "docai",
      "columns": {
        "id": {
          "name": "id",
          "type": "uuid",
          "primaryKey": true,
          "notNull": true,
          "default": "gen_random_uuid()"
        },
        "owner_id": {
          "name": "owner_id",
          "type": "text",
          "primaryKey": false,
          "notNull": true
        },
        "created_at": {
          "name": "created_at",
          "type": "timestamp with time zone",
          "primaryKey": false,
          "notNull": true,
          "default": "now()"
        }
      },
      "indexes": {},
      "foreignKeys": {
        "workspaces_owner_id_users_id_fk": {
          "name": "workspaces_owner_id_users_id_fk",
          "tableFrom": "workspaces",
          "tableTo": "users",
          "schemaTo": "docai",
          "columnsFrom": [
            "owner_id"
          ],
          "columnsTo": [
            "id"
          ],
          "onDelete": "cascade",
          "onUpdate": "no action"
        }
      },
      "compositePrimaryKeys": {},
      "uniqueConstraints": {},
      "policies": {},
      "checkConstraints": {},
      "isRLSEnabled": false
    }
  },
  "enums": {},
  "schemas": {
    "docai": "docai"
  },
  "sequences": {},
  "roles": {},
  "policies": {},
  "views": {},
  "_meta": {
    "columns": {},
    "schemas": {},
    "tables": {}
  }
}